gdasdb/__init__.py
gdasdb/gdasdb.py
gdasdb-0.0.1.dist-info/LICENSE
gdasdb-0.0.1.dist-info/METADATA
gdasdb-0.0.1.dist-info/WHEEL
gdasdb-0.0.1.dist-info/top_level.txt
gdasdb-0.0.1.dist-info/RECORD
